stlens-0.1.0.dist-info/METADATA
stlens-0.1.0.dist-info/RECORD
stlens-0.1.0.dist-info/WHEEL
stLENS/__init__.py
stLENS/stLENS.py
stLENS/calc.py
stLENS/librandom_matrix.so
stLENS/libperturb_omp.so
stLENS/PCA.py
stlens.libs/libgomp-d22c30c5.so.1.0.0
